components/counter.vhdl
library ieee;
use ieee.std_logic_1164.all;
use ieee.numeric_std.all;

entity counter is
    generic (
        SIZE : positive := 1;
        STEP : positive := 1;
        SEED : natural := 0;
        OVERFLOW : std_logic := '1'
        );
    port (
        clk     : in std_logic;
        reset_L : in std_logic := '0';
        enable  : in std_logic := '0';
        up_down : in std_logic := '0';
        cout    : out std_logic_vector(SIZE-1 downto 0)
    );
end entity counter;

architecture rtl of counter is
    constant MAX : unsigned(SIZE-1 downto 0) := (others => '1');
    constant MIN : unsigned(SIZE-1 downto 0) := (others => '0');

    signal count : unsigned(SIZE-1 downto 0);
begin
    process (clk, reset_L, enable, up_down)
    begin
        if (reset_L = '0') then
            count <= to_unsigned(SEED, SIZE);

        else 
            if(rising_edge(clk)) then
                if(enable = '1') then
                    if OVERFLOW = '1' then
                        if (up_down = '0') then
                            count <= count + STEP;
                        else
                            count <= count - STEP;
                        end if;

                    else
                        if (up_down = '0') then
                            if (count + STEP) /= MIN then
                                count <= count + STEP;
                            end if;
                        else
                            if (count - STEP) /= MAX then
                                count <= count - STEP;
                            end if;
                        end if;
                    end if;
                end if;
            end if;
        end if;
    end process;

    cout <= std_logic_vector(count);

end architecture;

testing/counter/counter_tb.vhd
library ieee;
use ieee.std_logic_1164.all;
use ieee.numeric_std.all;
use ieee.math_real.all;


entity counter_tb is
end entity counter_tb;

architecture behavior of counter_tb is

    component counter is
        generic (
            SIZE : positive := 1;
            STEP : positive := 1;
            SEED : natural := 0;
            OVERFLOW : std_logic := '1'
            );
        port (
            clk     : in std_logic;
            reset_L : in std_logic := '0';
            enable  : in std_logic := '0';
            up_down : in std_logic := '0';
            cout    : out std_logic_vector(SIZE-1 downto 0)
        );
    end component counter;

    signal clk     : std_logic;
    signal reset_L : std_logic;
    signal enable : std_logic;
    signal up_down : std_logic;
    signal cout : std_logic_vector(3 downto 0);
    
begin
    DUT: counter generic map (
        SIZE => 4, OVERFLOW => '1'
    )
    port map (
        clk => clk,
        reset_L => reset_L,
        enable => enable,
        up_down => up_down,
        cout => cout
    );

    process
    begin

        reset_L <= '0';
        up_down <= '0';
        enable <= '1';
        wait for 2 ns;
        reset_L <= '1';
        
        wait for 20 ns;
        up_down <= '1';


        

        wait;
    end process;
    
    clock_gen: process
    begin
        clk <= '0';
        wait for 0.5 ns;
        clk <= '1';
        wait for 0.5 ns;
    end process;
end architecture;

testing/counter/counter_tb.vcd
$date
  Mon Nov 29 15:38:58 2021
$end
$version
  GHDL v0
$end
$timescale
  1 fs
$end
$scope module standard $end
$upscope $end
$scope module std_logic_1164 $end
$upscope $end
$scope module numeric_std $end
$upscope $end
$scope module math_real $end
$upscope $end
$scope module counter_tb $end
$var reg 1 ! clk $end
$var reg 1 " reset_l $end
$var reg 1 # enable $end
$var reg 1 $ up_down $end
$var reg 4 % cout[3:0] $end
$scope module dut $end
$var reg 1 & clk $end
$var reg 1 ' reset_l $end
$var reg 1 ( enable $end
$var reg 1 ) up_down $end
$var reg 4 * cout[3:0] $end
$var reg 4 + count[3:0] $end
$upscope $end
$upscope $end
$enddefinitions $end
#0
0!
0"
1#
0$
b0000 %
0&
0'
1(
0)
b0000 *
b0000 +
#500000
1!
1&
#1000000
0!
0&
#1500000
1!
1&
#2000000
0!
1"
0&
1'
#2500000
1!
b0001 %
1&
b0001 *
b0001 +
#3000000
0!
0&
#3500000
1!
b0010 %
1&
b0010 *
b0010 +
#4000000
0!
0&
#4500000
1!
b0011 %
1&
b0011 *
b0011 +
#5000000
0!
0&
#5500000
1!
b0100 %
1&
b0100 *
b0100 +
#6000000
0!
0&
#6500000
1!
b0101 %
1&
b0101 *
b0101 +
#7000000
0!
0&
#7500000
1!
b0110 %
1&
b0110 *
b0110 +
#8000000
0!
0&
#8500000
1!
b0111 %
1&
b0111 *
b0111 +
#9000000
0!
0&
#9500000
1!
b1000 %
1&
b1000 *
b1000 +
#10000000
0!
0&
#10500000
1!
b1001 %
1&
b1001 *
b1001 +
#11000000
0!
0&
#11500000
1!
b1010 %
1&
b1010 *
b1010 +
#12000000
0!
0&
#12500000
1!
b1011 %
1&
b1011 *
b1011 +
#13000000
0!
0&
#13500000
1!
b1100 %
1&
b1100 *
b1100 +
#14000000
0!
0&
#14500000
1!
b1101 %
1&
b1101 *
b1101 +
#15000000
0!
0&
#15500000
1!
b1110 %
1&
b1110 *
b1110 +
#16000000
0!
0&
#16500000
1!
b1111 %
1&
b1111 *
b1111 +
#17000000
0!
0&
#17500000
1!
b0000 %
1&
b0000 *
b0000 +
#18000000
0!
0&
#18500000
1!
b0001 %
1&
b0001 *
b0001 +
#19000000
0!
0&
#19500000
1!
b0010 %
1&
b0010 *
b0010 +
#20000000
0!
0&
#20500000
1!
b0011 %
1&
b0011 *
b0011 +
#21000000
0!
0&
#21500000
1!
b0100 %
1&
b0100 *
b0100 +
#22000000
0!
1$
0&
1)
#22500000
1!
b0011 %
1&
b0011 *
b0011 +
#23000000
0!
0&
#23500000
1!
b0010 %
1&
b0010 *
b0010 +
#24000000
0!
0&
#24500000
1!
b0001 %
1&
b0001 *
b0001 +
#25000000
0!
0&
#25500000
1!
b0000 %
1&
b0000 *
b0000 +
#26000000
0!
0&
#26500000
1!
b1111 %
1&
b1111 *
b1111 +
#27000000
0!
0&
#27500000
1!
b1110 %
1&
b1110 *
b1110 +
#28000000
0!
0&
#28500000
1!
b1101 %
1&
b1101 *
b1101 +
#29000000
0!
0&
#29500000
1!
b1100 %
1&
b1100 *
b1100 +
#30000000
0!
0&
#30500000
1!
b1011 %
1&
b1011 *
b1011 +
#31000000
0!
0&
#31500000
1!
b1010 %
1&
b1010 *
b1010 +
#32000000
0!
0&
#32500000
1!
b1001 %
1&
b1001 *
b1001 +
#33000000
0!
0&
#33500000
1!
b1000 %
1&
b1000 *
b1000 +
#34000000
0!
0&
#34500000
1!
b0111 %
1&
b0111 *
b0111 +
#35000000
0!
0&
#35500000
1!
b0110 %
1&
b0110 *
b0110 +
#36000000
0!
0&
#36500000
1!
b0101 %
1&
b0101 *
b0101 +
#37000000
0!
0&
#37500000
1!
b0100 %
1&
b0100 *
b0100 +
#38000000
0!
0&
#38500000
1!
b0011 %
1&
b0011 *
b0011 +
#39000000
0!
0&
#39500000
1!
b0010 %
1&
b0010 *
b0010 +
#40000000
0!
0&
#40500000
1!
b0001 %
1&
b0001 *
b0001 +
#41000000
0!
0&
#41500000
1!
b0000 %
1&
b0000 *
b0000 +
#42000000
0!
0&
#42500000
1!
b1111 %
1&
b1111 *
b1111 +
#43000000
0!
0&
#43500000
1!
b1110 %
1&
b1110 *
b1110 +
#44000000
0!
0&
#44500000
1!
b1101 %
1&
b1101 *
b1101 +
#45000000
0!
0&
#45500000
1!
b1100 %
1&
b1100 *
b1100 +
#46000000
0!
0&
#46500000
1!
b1011 %
1&
b1011 *
b1011 +
#47000000
0!
0&
#47500000
1!
b1010 %
1&
b1010 *
b1010 +
#48000000
0!
0&
#48500000
1!
b1001 %
1&
b1001 *
b1001 +
#49000000
0!
0&
#49500000
1!
b1000 %
1&
b1000 *
b1000 +
#50000000
0!
0&
#50500000
1!
b0111 %
1&
b0111 *
b0111 +
#51000000
0!
0&
#51500000
1!
b0110 %
1&
b0110 *
b0110 +
#52000000
0!
0&
#52500000
1!
b0101 %
1&
b0101 *
b0101 +
#53000000
0!
0&
#53500000
1!
b0100 %
1&
b0100 *
b0100 +
#54000000
0!
0&
#54500000
1!
b0011 %
1&
b0011 *
b0011 +
#55000000
0!
0&
#55500000
1!
b0010 %
1&
b0010 *
b0010 +
#56000000
0!
0&
#56500000
1!
b0001 %
1&
b0001 *
b0001 +
#57000000
0!
0&
#57500000
1!
b0000 %
1&
b0000 *
b0000 +
#58000000
0!
0&
#58500000
1!
b1111 %
1&
b1111 *
b1111 +
#59000000
0!
0&
#59500000
1!
b1110 %
1&
b1110 *
b1110 +
#60000000
0!
0&
#60500000
1!
b1101 %
1&
b1101 *
b1101 +
#61000000
0!
0&
#61500000
1!
b1100 %
1&
b1100 *
b1100 +
#62000000
0!
0&
#62500000
1!
b1011 %
1&
b1011 *
b1011 +
#63000000
0!
0&
#63500000
1!
b1010 %
1&
b1010 *
b1010 +
#64000000
0!
0&
#64500000
1!
b1001 %
1&
b1001 *
b1001 +
#65000000
0!
0&
#65500000
1!
b1000 %
1&
b1000 *
b1000 +
#66000000
0!
0&
#66500000
1!
b0111 %
1&
b0111 *
b0111 +
#67000000
0!
0&
#67500000
1!
b0110 %
1&
b0110 *
b0110 +
#68000000
0!
0&
#68500000
1!
b0101 %
1&
b0101 *
b0101 +
#69000000
0!
0&
#69500000
1!
b0100 %
1&
b0100 *
b0100 +
#70000000
0!
0&
#70500000
1!
b0011 %
1&
b0011 *
b0011 +
#71000000
0!
0&
#71500000
1!
b0010 %
1&
b0010 *
b0010 +
#72000000
0!
0&
#72500000
1!
b0001 %
1&
b0001 *
b0001 +
#73000000
0!
0&
#73500000
1!
b0000 %
1&
b0000 *
b0000 +
#74000000
0!
0&
#74500000
1!
b1111 %
1&
b1111 *
b1111 +
#75000000
0!
0&
#75500000
1!
b1110 %
1&
b1110 *
b1110 +
#76000000
0!
0&
#76500000
1!
b1101 %
1&
b1101 *
b1101 +
#77000000
0!
0&
#77500000
1!
b1100 %
1&
b1100 *
b1100 +
#78000000
0!
0&
#78500000
1!
b1011 %
1&
b1011 *
b1011 +
#79000000
0!
0&
#79500000
1!
b1010 %
1&
b1010 *
b1010 +
#80000000
0!
0&
#80500000
1!
b1001 %
1&
b1001 *
b1001 +
#81000000
0!
0&
#81500000
1!
b1000 %
1&
b1000 *
b1000 +
#82000000
0!
0&
#82500000
1!
b0111 %
1&
b0111 *
b0111 +
#83000000
0!
0&
#83500000
1!
b0110 %
1&
b0110 *
b0110 +
#84000000
0!
0&
#84500000
1!
b0101 %
1&
b0101 *
b0101 +
#85000000
0!
0&
#85500000
1!
b0100 %
1&
b0100 *
b0100 +
#86000000
0!
0&
#86500000
1!
b0011 %
1&
b0011 *
b0011 +
#87000000
0!
0&
#87500000
1!
b0010 %
1&
b0010 *
b0010 +
#88000000
0!
0&
#88500000
1!
b0001 %
1&
b0001 *
b0001 +
#89000000
0!
0&
#89500000
1!
b0000 %
1&
b0000 *
b0000 +
#90000000
0!
0&
#90500000
1!
b1111 %
1&
b1111 *
b1111 +
#91000000
0!
0&
#91500000
1!
b1110 %
1&
b1110 *
b1110 +
#92000000
0!
0&
#92500000
1!
b1101 %
1&
b1101 *
b1101 +
#93000000
0!
0&
#93500000
1!
b1100 %
1&
b1100 *
b1100 +
#94000000
0!
0&
#94500000
1!
b1011 %
1&
b1011 *
b1011 +
#95000000
0!
0&
#95500000
1!
b1010 %
1&
b1010 *
b1010 +
#96000000
0!
0&
#96500000
1!
b1001 %
1&
b1001 *
b1001 +
#97000000
0!
0&
#97500000
1!
b1000 %
1&
b1000 *
b1000 +
#98000000
0!
0&
#98500000
1!
b0111 %
1&
b0111 *
b0111 +
#99000000
0!
0&
#99500000
1!
b0110 %
1&
b0110 *
b0110 +
#100000000
0!
0&
#100500000
1!
b0101 %
1&
b0101 *
b0101 +
#101000000
0!
0&
#101500000
1!
b0100 %
1&
b0100 *
b0100 +
#102000000
0!
0&
#102500000
1!
b0011 %
1&
b0011 *
b0011 +
#103000000
0!
0&
#103500000
1!
b0010 %
1&
b0010 *
b0010 +
#104000000
0!
0&
#104500000
1!
b0001 %
1&
b0001 *
b0001 +
#105000000
0!
0&
#105500000
1!
b0000 %
1&
b0000 *
b0000 +
#106000000
0!
0&
#106500000
1!
b1111 %
1&
b1111 *
b1111 +
#107000000
0!
0&
#107500000
1!
b1110 %
1&
b1110 *
b1110 +
#108000000
0!
0&
#108500000
1!
b1101 %
1&
b1101 *
b1101 +
#109000000
0!
0&
#109500000
1!
b1100 %
1&
b1100 *
b1100 +
#110000000
0!
0&
#110500000
1!
b1011 %
1&
b1011 *
b1011 +
#111000000
0!
0&
#111500000
1!
b1010 %
1&
b1010 *
b1010 +
#112000000
0!
0&
#112500000
1!
b1001 %
1&
b1001 *
b1001 +
#113000000
0!
0&
#113500000
1!
b1000 %
1&
b1000 *
b1000 +
#114000000
0!
0&
#114500000
1!
b0111 %
1&
b0111 *
b0111 +
#115000000
0!
0&
#115500000
1!
b0110 %
1&
b0110 *
b0110 +
#116000000
0!
0&
#116500000
1!
b0101 %
1&
b0101 *
b0101 +
#117000000
0!
0&
#117500000
1!
b0100 %
1&
b0100 *
b0100 +
#118000000
0!
0&
#118500000
1!
b0011 %
1&
b0011 *
b0011 +
#119000000
0!
0&
#119500000
1!
b0010 %
1&
b0010 *
b0010 +
#120000000
0!
0&
#120500000
1!
b0001 %
1&
b0001 *
b0001 +
#121000000
0!
0&
#121500000
1!
b0000 %
1&
b0000 *
b0000 +
#122000000
0!
0&
#122500000
1!
b1111 %
1&
b1111 *
b1111 +
#123000000
0!
0&
#123500000
1!
b1110 %
1&
b1110 *
b1110 +
#124000000
0!
0&
#124500000
1!
b1101 %
1&
b1101 *
b1101 +
#125000000
0!
0&
#125500000
1!
b1100 %
1&
b1100 *
b1100 +
#126000000
0!
0&
#126500000
1!
b1011 %
1&
b1011 *
b1011 +
#127000000
0!
0&
#127500000
1!
b1010 %
1&
b1010 *
b1010 +
#128000000
0!
0&
#128500000
1!
b1001 %
1&
b1001 *
b1001 +
#129000000
0!
0&
#129500000
1!
b1000 %
1&
b1000 *
b1000 +
#130000000
0!
0&
#130500000
1!
b0111 %
1&
b0111 *
b0111 +
#131000000
0!
0&
#131500000
1!
b0110 %
1&
b0110 *
b0110 +
#132000000
0!
0&
#132500000
1!
b0101 %
1&
b0101 *
b0101 +
#133000000
0!
0&
#133500000
1!
b0100 %
1&
b0100 *
b0100 +
#134000000
0!
0&
#134500000
1!
b0011 %
1&
b0011 *
b0011 +
#135000000
0!
0&
#135500000
1!
b0010 %
1&
b0010 *
b0010 +
#136000000
0!
0&
#136500000
1!
b0001 %
1&
b0001 *
b0001 +
#137000000
0!
0&
#137500000
1!
b0000 %
1&
b0000 *
b0000 +
#138000000
0!
0&
#138500000
1!
b1111 %
1&
b1111 *
b1111 +
#139000000
0!
0&
#139500000
1!
b1110 %
1&
b1110 *
b1110 +
#140000000
0!
0&
#140500000
1!
b1101 %
1&
b1101 *
b1101 +
#141000000
0!
0&
#141500000
1!
b1100 %
1&
b1100 *
b1100 +
#142000000
0!
0&
#142500000
1!
b1011 %
1&
b1011 *
b1011 +
#143000000
0!
0&
#143500000
1!
b1010 %
1&
b1010 *
b1010 +
#144000000
0!
0&
#144500000
1!
b1001 %
1&
b1001 *
b1001 +
#145000000
0!
0&
#145500000
1!
b1000 %
1&
b1000 *
b1000 +
#146000000
0!
0&
#146500000
1!
b0111 %
1&
b0111 *
b0111 +
#147000000
0!
0&
#147500000
1!
b0110 %
1&
b0110 *
b0110 +
#148000000
0!
0&
#148500000
1!
b0101 %
1&
b0101 *
b0101 +
#149000000
0!
0&
#149500000
1!
b0100 %
1&
b0100 *
b0100 +
#150000000
0!
0&
#150500000
1!
b0011 %
1&
b0011 *
b0011 +
#151000000
0!
0&
#151500000
1!
b0010 %
1&
b0010 *
b0010 +
#152000000
0!
0&
#152500000
1!
b0001 %
1&
b0001 *
b0001 +
#153000000
0!
0&
#153500000
1!
b0000 %
1&
b0000 *
b0000 +
#154000000
0!
0&
#154500000
1!
b1111 %
1&
b1111 *
b1111 +
#155000000
0!
0&
#155500000
1!
b1110 %
1&
b1110 *
b1110 +
#156000000
0!
0&
#156500000
1!
b1101 %
1&
b1101 *
b1101 +
#157000000
0!
0&
#157500000
1!
b1100 %
1&
b1100 *
b1100 +
#158000000
0!
0&
#158500000
1!
b1011 %
1&
b1011 *
b1011 +
#159000000
0!
0&
#159500000
1!
b1010 %
1&
b1010 *
b1010 +
#160000000
0!
0&
#160500000
1!
b1001 %
1&
b1001 *
b1001 +
#161000000
0!
0&
#161500000
1!
b1000 %
1&
b1000 *
b1000 +
#162000000
0!
0&
#162500000
1!
b0111 %
1&
b0111 *
b0111 +
#163000000
0!
0&
#163500000
1!
b0110 %
1&
b0110 *
b0110 +
#164000000
0!
0&
#164500000
1!
b0101 %
1&
b0101 *
b0101 +
#165000000
0!
0&
#165500000
1!
b0100 %
1&
b0100 *
b0100 +
#166000000
0!
0&
#166500000
1!
b0011 %
1&
b0011 *
b0011 +
#167000000
0!
0&
#167500000
1!
b0010 %
1&
b0010 *
b0010 +
#168000000
0!
0&
#168500000
1!
b0001 %
1&
b0001 *
b0001 +
#169000000
0!
0&
#169500000
1!
b0000 %
1&
b0000 *
b0000 +
#170000000
0!
0&
#170500000
1!
b1111 %
1&
b1111 *
b1111 +
#171000000
0!
0&
#171500000
1!
b1110 %
1&
b1110 *
b1110 +
#172000000
0!
0&
#172500000
1!
b1101 %
1&
b1101 *
b1101 +
#173000000
0!
0&
#173500000
1!
b1100 %
1&
b1100 *
b1100 +
#174000000
0!
0&
#174500000
1!
b1011 %
1&
b1011 *
b1011 +
#175000000
0!
0&
#175500000
1!
b1010 %
1&
b1010 *
b1010 +
#176000000
0!
0&
#176500000
1!
b1001 %
1&
b1001 *
b1001 +
#177000000
0!
0&
#177500000
1!
b1000 %
1&
b1000 *
b1000 +
#178000000
0!
0&
#178500000
1!
b0111 %
1&
b0111 *
b0111 +
#179000000
0!
0&
#179500000
1!
b0110 %
1&
b0110 *
b0110 +
#180000000
0!
0&
#180500000
1!
b0101 %
1&
b0101 *
b0101 +
#181000000
0!
0&
#181500000
1!
b0100 %
1&
b0100 *
b0100 +
#182000000
0!
0&
#182500000
1!
b0011 %
1&
b0011 *
b0011 +
#183000000
0!
0&
#183500000
1!
b0010 %
1&
b0010 *
b0010 +
#184000000
0!
0&
#184500000
1!
b0001 %
1&
b0001 *
b0001 +
#185000000
0!
0&
#185500000
1!
b0000 %
1&
b0000 *
b0000 +
#186000000
0!
0&
#186500000
1!
b1111 %
1&
b1111 *
b1111 +
#187000000
0!
0&
#187500000
1!
b1110 %
1&
b1110 *
b1110 +
#188000000
0!
0&
#188500000
1!
b1101 %
1&
b1101 *
b1101 +
#189000000
0!
0&
#189500000
1!
b1100 %
1&
b1100 *
b1100 +
#190000000
0!
0&
#190500000
1!
b1011 %
1&
b1011 *
b1011 +
#191000000
0!
0&
#191500000
1!
b1010 %
1&
b1010 *
b1010 +
#192000000
0!
0&
#192500000
1!
b1001 %
1&
b1001 *
b1001 +
#193000000
0!
0&
#193500000
1!
b1000 %
1&
b1000 *
b1000 +
#194000000
0!
0&
#194500000
1!
b0111 %
1&
b0111 *
b0111 +
#195000000
0!
0&
#195500000
1!
b0110 %
1&
b0110 *
b0110 +
#196000000
0!
0&
#196500000
1!
b0101 %
1&
b0101 *
b0101 +
#197000000
0!
0&
#197500000
1!
b0100 %
1&
b0100 *
b0100 +
#198000000
0!
0&
#198500000
1!
b0011 %
1&
b0011 *
b0011 +
#199000000
0!
0&
#199500000
1!
b0010 %
1&
b0010 *
b0010 +
#200000000
0!
0&
#200500000
1!
b0001 %
1&
b0001 *
b0001 +
#201000000
0!
0&
#201500000
1!
b0000 %
1&
b0000 *
b0000 +
#202000000
0!
0&
#202500000
1!
b1111 %
1&
b1111 *
b1111 +
#203000000
0!
0&
#203500000
1!
b1110 %
1&
b1110 *
b1110 +
#204000000
0!
0&
#204500000
1!
b1101 %
1&
b1101 *
b1101 +
#205000000
0!
0&
#205500000
1!
b1100 %
1&
b1100 *
b1100 +
#206000000
0!
0&
#206500000
1!
b1011 %
1&
b1011 *
b1011 +
#207000000
0!
0&
#207500000
1!
b1010 %
1&
b1010 *
b1010 +
#208000000
0!
0&
#208500000
1!
b1001 %
1&
b1001 *
b1001 +
#209000000
0!
0&
#209500000
1!
b1000 %
1&
b1000 *
b1000 +
#210000000
0!
0&
#210500000
1!
b0111 %
1&
b0111 *
b0111 +
#211000000
0!
0&
#211500000
1!
b0110 %
1&
b0110 *
b0110 +
#212000000
0!
0&
#212500000
1!
b0101 %
1&
b0101 *
b0101 +
#213000000
0!
0&
#213500000
1!
b0100 %
1&
b0100 *
b0100 +
#214000000
0!
0&
#214500000
1!
b0011 %
1&
b0011 *
b0011 +
#215000000
0!
0&
#215500000
1!
b0010 %
1&
b0010 *
b0010 +
#216000000
0!
0&
#216500000
1!
b0001 %
1&
b0001 *
b0001 +
#217000000
0!
0&
#217500000
1!
b0000 %
1&
b0000 *
b0000 +
#218000000
0!
0&
#218500000
1!
b1111 %
1&
b1111 *
b1111 +
#219000000
0!
0&
#219500000
1!
b1110 %
1&
b1110 *
b1110 +
#220000000
0!
0&
#220500000
1!
b1101 %
1&
b1101 *
b1101 +
#221000000
0!
0&
#221500000
1!
b1100 %
1&
b1100 *
b1100 +
#222000000
0!
0&
#222500000
1!
b1011 %
1&
b1011 *
b1011 +
#223000000
0!
0&
#223500000
1!
b1010 %
1&
b1010 *
b1010 +
#224000000
0!
0&
#224500000
1!
b1001 %
1&
b1001 *
b1001 +
#225000000
0!
0&
#225500000
1!
b1000 %
1&
b1000 *
b1000 +
#226000000
0!
0&
#226500000
1!
b0111 %
1&
b0111 *
b0111 +
#227000000
0!
0&
#227500000
1!
b0110 %
1&
b0110 *
b0110 +
#228000000
0!
0&
#228500000
1!
b0101 %
1&
b0101 *
b0101 +
#229000000
0!
0&
#229500000
1!
b0100 %
1&
b0100 *
b0100 +
#230000000
0!
0&
#230500000
1!
b0011 %
1&
b0011 *
b0011 +
#231000000
0!
0&
#231500000
1!
b0010 %
1&
b0010 *
b0010 +
#232000000
0!
0&
#232500000
1!
b0001 %
1&
b0001 *
b0001 +
#233000000
0!
0&
#233500000
1!
b0000 %
1&
b0000 *
b0000 +
#234000000
0!
0&
#234500000
1!
b1111 %
1&
b1111 *
b1111 +
#235000000
0!
0&
#235500000
1!
b1110 %
1&
b1110 *
b1110 +
#236000000
0!
0&
#236500000
1!
b1101 %
1&
b1101 *
b1101 +
#237000000
0!
0&
#237500000
1!
b1100 %
1&
b1100 *
b1100 +
#238000000
0!
0&
#238500000
1!
b1011 %
1&
b1011 *
b1011 +
#239000000
0!
0&
#239500000
1!
b1010 %
1&
b1010 *
b1010 +
#240000000
0!
0&
#240500000
1!
b1001 %
1&
b1001 *
b1001 +
#241000000
0!
0&
#241500000
1!
b1000 %
1&
b1000 *
b1000 +
#242000000
0!
0&
#242500000
1!
b0111 %
1&
b0111 *
b0111 +
#243000000
0!
0&
#243500000
1!
b0110 %
1&
b0110 *
b0110 +
#244000000
0!
0&
#244500000
1!
b0101 %
1&
b0101 *
b0101 +
#245000000
0!
0&
#245500000
1!
b0100 %
1&
b0100 *
b0100 +
#246000000
0!
0&
#246500000
1!
b0011 %
1&
b0011 *
b0011 +
#247000000
0!
0&
#247500000
1!
b0010 %
1&
b0010 *
b0010 +
#248000000
0!
0&
#248500000
1!
b0001 %
1&
b0001 *
b0001 +
#249000000
0!
0&
#249500000
1!
b0000 %
1&
b0000 *
b0000 +
#250000000
0!
0&
#250500000
1!
b1111 %
1&
b1111 *
b1111 +
#251000000
0!
0&
#251500000
1!
b1110 %
1&
b1110 *
b1110 +
#252000000
0!
0&
#252500000
1!
b1101 %
1&
b1101 *
b1101 +
#253000000
0!
0&
#253500000
1!
b1100 %
1&
b1100 *
b1100 +
#254000000
0!
0&
#254500000
1!
b1011 %
1&
b1011 *
b1011 +
#255000000
0!
0&
#255500000
1!
b1010 %
1&
b1010 *
b1010 +
#256000000
0!
0&
#256500000
1!
b1001 %
1&
b1001 *
b1001 +
#257000000
0!
0&
#257500000
1!
b1000 %
1&
b1000 *
b1000 +
#258000000
0!
0&
#258500000
1!
b0111 %
1&
b0111 *
b0111 +
#259000000
0!
0&
#259500000
1!
b0110 %
1&
b0110 *
b0110 +
#260000000
0!
0&
#260500000
1!
b0101 %
1&
b0101 *
b0101 +
#261000000
0!
0&
#261500000
1!
b0100 %
1&
b0100 *
b0100 +
#262000000
0!
0&
#262500000
1!
b0011 %
1&
b0011 *
b0011 +
#263000000
0!
0&
#263500000
1!
b0010 %
1&
b0010 *
b0010 +
#264000000
0!
0&
#264500000
1!
b0001 %
1&
b0001 *
b0001 +
#265000000
0!
0&
#265500000
1!
b0000 %
1&
b0000 *
b0000 +
#266000000
0!
0&
#266500000
1!
b1111 %
1&
b1111 *
b1111 +
#267000000
0!
0&
#267500000
1!
b1110 %
1&
b1110 *
b1110 +
#268000000
0!
0&
#268500000
1!
b1101 %
1&
b1101 *
b1101 +
#269000000
0!
0&
#269500000
1!
b1100 %
1&
b1100 *
b1100 +
#270000000
0!
0&
#270500000
1!
b1011 %
1&
b1011 *
b1011 +
#271000000
0!
0&
#271500000
1!
b1010 %
1&
b1010 *
b1010 +
#272000000
0!
0&
#272500000
1!
b1001 %
1&
b1001 *
b1001 +
#273000000
0!
0&
#273500000
1!
b1000 %
1&
b1000 *
b1000 +
#274000000
0!
0&
#274500000
1!
b0111 %
1&
b0111 *
b0111 +
#275000000
0!
0&
#275500000
1!
b0110 %
1&
b0110 *
b0110 +
#276000000
0!
0&
#276500000
1!
b0101 %
1&
b0101 *
b0101 +
#277000000
0!
0&
#277500000
1!
b0100 %
1&
b0100 *
b0100 +
#278000000
0!
0&
#278500000
1!
b0011 %
1&
b0011 *
b0011 +
#279000000
0!
0&
#279500000
1!
b0010 %
1&
b0010 *
b0010 +
#280000000
0!
0&
#280500000
1!
b0001 %
1&
b0001 *
b0001 +
#281000000
0!
0&
#281500000
1!
b0000 %
1&
b0000 *
b0000 +
#282000000
0!
0&
#282500000
1!
b1111 %
1&
b1111 *
b1111 +
#283000000
0!
0&
#283500000
1!
b1110 %
1&
b1110 *
b1110 +
#284000000
0!
0&
#284500000
1!
b1101 %
1&
b1101 *
b1101 +
#285000000
0!
0&
#285500000
1!
b1100 %
1&
b1100 *
b1100 +
#286000000
0!
0&
#286500000
1!
b1011 %
1&
b1011 *
b1011 +
#287000000
0!
0&
#287500000
1!
b1010 %
1&
b1010 *
b1010 +
#288000000
0!
0&
#288500000
1!
b1001 %
1&
b1001 *
b1001 +
#289000000
0!
0&
#289500000
1!
b1000 %
1&
b1000 *
b1000 +
#290000000
0!
0&
#290500000
1!
b0111 %
1&
b0111 *
b0111 +
#291000000
0!
0&
#291500000
1!
b0110 %
1&
b0110 *
b0110 +
#292000000
0!
0&
#292500000
1!
b0101 %
1&
b0101 *
b0101 +
#293000000
0!
0&
#293500000
1!
b0100 %
1&
b0100 *
b0100 +
#294000000
0!
0&
#294500000
1!
b0011 %
1&
b0011 *
b0011 +
#295000000
0!
0&
#295500000
1!
b0010 %
1&
b0010 *
b0010 +
#296000000
0!
0&
#296500000
1!
b0001 %
1&
b0001 *
b0001 +
#297000000
0!
0&
#297500000
1!
b0000 %
1&
b0000 *
b0000 +
#298000000
0!
0&
#298500000
1!
b1111 %
1&
b1111 *
b1111 +
#299000000
0!
0&
#299500000
1!
b1110 %
1&
b1110 *
b1110 +
