components/clk_div.vhdl
library ieee;
use ieee.std_logic_1164.all;
use ieee.numeric_std.all;
use ieee.math_real.all;

entity clk_div is
    port (
        clk_in  : in std_logic;
        div     : in integer;       -- rounds down to closest even number
        clk_out : buffer std_logic := '0'
    );
end entity clk_div;

architecture rtl of clk_div is
begin
    process (clk_in)
        variable count : integer := 0;
    begin
        if div = 1 then
            clk_out <= clk_in;
        else
            if(rising_edge(clk_in) and div > 0) then
                count := count + 2; --I am to tired to explain this, but don't change it

                if count >= div-1 then
                    clk_out <= not clk_out;
                    count := 0;
                end if;
            end if;
        end if;
    end process;
end architecture;

testing/clk_div/counter_tb.vhd
library ieee;
use ieee.std_logic_1164.all;
use ieee.numeric_std.all;
use ieee.math_real.all;


entity counter_tb is
end entity counter_tb;

architecture behavior of counter_tb is

    component clk_div is
        port (
            clk_in  : in std_logic;
            div     : in integer;
            clk_out : buffer std_logic := '0'
        );
    end component clk_div;

    signal clk     : std_logic;
    signal div     : integer := 0;
    signal clk_out : std_logic;
    
begin
    DUT: clk_div
         port map (
            clk, div, clk_out
         );

    process
    begin

        wait for 16 ns;
        div <= 1;
        wait for 16 ns;
        div <= 2;
        wait for 16 ns;
        div <= 3;
        wait for 16 ns;
        div <= 4;
        wait for 40 ns;
        div <= 5;
        wait for 40 ns;
        div <= 7;
        wait for 40 ns;
        div <= 0;
        


        

        wait;
    end process;
    
    clock_gen: process
    begin
        clk <= '0';
        wait for 0.5 ns;
        clk <= '1';
        wait for 0.5 ns;
    end process;
end architecture;

testing/clk_div/counter_tb.vcd
$date
  Sun Nov  7 23:28:57 2021
$end
$version
  GHDL v0
$end
$timescale
  1 fs
$end
$scope module standard $end
$upscope $end
$scope module std_logic_1164 $end
$upscope $end
$scope module numeric_std $end
$upscope $end
$scope module math_real $end
$upscope $end
$scope module counter_tb $end
$var reg 1 ! clk $end
$var integer 32 " div $end
$var reg 1 # clk_out $end
$scope module dut $end
$var reg 1 $ clk_in $end
$var integer 32 % div $end
$var reg 1 & clk_out $end
$upscope $end
$upscope $end
$enddefinitions $end
#0
0!
b0 "
0#
0$
b0 %
0&
#500000
1!
1$
#1000000
0!
0$
#1500000
1!
1$
#2000000
0!
0$
#2500000
1!
1$
#3000000
0!
0$
#3500000
1!
1$
#4000000
0!
0$
#4500000
1!
1$
#5000000
0!
0$
#5500000
1!
1$
#6000000
0!
0$
#6500000
1!
1$
#7000000
0!
0$
#7500000
1!
1$
#8000000
0!
0$
#8500000
1!
1$
#9000000
0!
0$
#9500000
1!
1$
#10000000
0!
0$
#10500000
1!
1$
#11000000
0!
0$
#11500000
1!
1$
#12000000
0!
0$
#12500000
1!
1$
#13000000
0!
0$
#13500000
1!
1$
#14000000
0!
0$
#14500000
1!
1$
#15000000
0!
0$
#15500000
1!
1$
#16000000
0!
b1 "
0$
b1 %
#16500000
1!
1#
1$
1&
#17000000
0!
0#
0$
0&
#17500000
1!
1#
1$
1&
#18000000
0!
0#
0$
0&
#18500000
1!
1#
1$
1&
#19000000
0!
0#
0$
0&
#19500000
1!
1#
1$
1&
#20000000
0!
0#
0$
0&
#20500000
1!
1#
1$
1&
#21000000
0!
0#
0$
0&
#21500000
1!
1#
1$
1&
#22000000
0!
0#
0$
0&
#22500000
1!
1#
1$
1&
#23000000
0!
0#
0$
0&
#23500000
1!
1#
1$
1&
#24000000
0!
0#
0$
0&
#24500000
1!
1#
1$
1&
#25000000
0!
0#
0$
0&
#25500000
1!
1#
1$
1&
#26000000
0!
0#
0$
0&
#26500000
1!
1#
1$
1&
#27000000
0!
0#
0$
0&
#27500000
1!
1#
1$
1&
#28000000
0!
0#
0$
0&
#28500000
1!
1#
1$
1&
#29000000
0!
0#
0$
0&
#29500000
1!
1#
1$
1&
#30000000
0!
0#
0$
0&
#30500000
1!
1#
1$
1&
#31000000
0!
0#
0$
0&
#31500000
1!
1#
1$
1&
#32000000
0!
b10 "
0$
b10 %
#32500000
1!
0#
1$
0&
#33000000
0!
0$
#33500000
1!
1#
1$
1&
#34000000
0!
0$
#34500000
1!
0#
1$
0&
#35000000
0!
0$
#35500000
1!
1#
1$
1&
#36000000
0!
0$
#36500000
1!
0#
1$
0&
#37000000
0!
0$
#37500000
1!
1#
1$
1&
#38000000
0!
0$
#38500000
1!
0#
1$
0&
#39000000
0!
0$
#39500000
1!
1#
1$
1&
#40000000
0!
0$
#40500000
1!
0#
1$
0&
#41000000
0!
0$
#41500000
1!
1#
1$
1&
#42000000
0!
0$
#42500000
1!
0#
1$
0&
#43000000
0!
0$
#43500000
1!
1#
1$
1&
#44000000
0!
0$
#44500000
1!
0#
1$
0&
#45000000
0!
0$
#45500000
1!
1#
1$
1&
#46000000
0!
0$
#46500000
1!
0#
1$
0&
#47000000
0!
0$
#47500000
1!
1#
1$
1&
#48000000
0!
b11 "
0$
b11 %
#48500000
1!
0#
1$
0&
#49000000
0!
0$
#49500000
1!
1#
1$
1&
#50000000
0!
0$
#50500000
1!
0#
1$
0&
#51000000
0!
0$
#51500000
1!
1#
1$
1&
#52000000
0!
0$
#52500000
1!
0#
1$
0&
#53000000
0!
0$
#53500000
1!
1#
1$
1&
#54000000
0!
0$
#54500000
1!
0#
1$
0&
#55000000
0!
0$
#55500000
1!
1#
1$
1&
#56000000
0!
0$
#56500000
1!
0#
1$
0&
#57000000
0!
0$
#57500000
1!
1#
1$
1&
#58000000
0!
0$
#58500000
1!
0#
1$
0&
#59000000
0!
0$
#59500000
1!
1#
1$
1&
#60000000
0!
0$
#60500000
1!
0#
1$
0&
#61000000
0!
0$
#61500000
1!
1#
1$
1&
#62000000
0!
0$
#62500000
1!
0#
1$
0&
#63000000
0!
0$
#63500000
1!
1#
1$
1&
#64000000
0!
b100 "
0$
b100 %
#64500000
1!
1$
#65000000
0!
0$
#65500000
1!
0#
1$
0&
#66000000
0!
0$
#66500000
1!
1$
#67000000
0!
0$
#67500000
1!
1#
1$
1&
#68000000
0!
0$
#68500000
1!
1$
#69000000
0!
0$
#69500000
1!
0#
1$
0&
#70000000
0!
0$
#70500000
1!
1$
#71000000
0!
0$
#71500000
1!
1#
1$
1&
#72000000
0!
0$
#72500000
1!
1$
#73000000
0!
0$
#73500000
1!
0#
1$
0&
#74000000
0!
0$
#74500000
1!
1$
#75000000
0!
0$
#75500000
1!
1#
1$
1&
#76000000
0!
0$
#76500000
1!
1$
#77000000
0!
0$
#77500000
1!
0#
1$
0&
#78000000
0!
0$
#78500000
1!
1$
#79000000
0!
0$
#79500000
1!
1#
1$
1&
#80000000
0!
0$
#80500000
1!
1$
#81000000
0!
0$
#81500000
1!
0#
1$
0&
#82000000
0!
0$
#82500000
1!
1$
#83000000
0!
0$
#83500000
1!
1#
1$
1&
#84000000
0!
0$
#84500000
1!
1$
#85000000
0!
0$
#85500000
1!
0#
1$
0&
#86000000
0!
0$
#86500000
1!
1$
#87000000
0!
0$
#87500000
1!
1#
1$
1&
#88000000
0!
0$
#88500000
1!
1$
#89000000
0!
0$
#89500000
1!
0#
1$
0&
#90000000
0!
0$
#90500000
1!
1$
#91000000
0!
0$
#91500000
1!
1#
1$
1&
#92000000
0!
0$
#92500000
1!
1$
#93000000
0!
0$
#93500000
1!
0#
1$
0&
#94000000
0!
0$
#94500000
1!
1$
#95000000
0!
0$
#95500000
1!
1#
1$
1&
#96000000
0!
0$
#96500000
1!
1$
#97000000
0!
0$
#97500000
1!
0#
1$
0&
#98000000
0!
0$
#98500000
1!
1$
#99000000
0!
0$
#99500000
1!
1#
1$
1&
#100000000
0!
0$
#100500000
1!
1$
#101000000
0!
0$
#101500000
1!
0#
1$
0&
#102000000
0!
0$
#102500000
1!
1$
#103000000
0!
0$
#103500000
1!
1#
1$
1&
#104000000
0!
b101 "
0$
b101 %
#104500000
1!
1$
#105000000
0!
0$
#105500000
1!
0#
1$
0&
#106000000
0!
0$
#106500000
1!
1$
#107000000
0!
0$
#107500000
1!
1#
1$
1&
#108000000
0!
0$
#108500000
1!
1$
#109000000
0!
0$
#109500000
1!
0#
1$
0&
#110000000
0!
0$
#110500000
1!
1$
#111000000
0!
0$
#111500000
1!
1#
1$
1&
#112000000
0!
0$
#112500000
1!
1$
#113000000
0!
0$
#113500000
1!
0#
1$
0&
#114000000
0!
0$
#114500000
1!
1$
#115000000
0!
0$
#115500000
1!
1#
1$
1&
#116000000
0!
0$
#116500000
1!
1$
#117000000
0!
0$
#117500000
1!
0#
1$
0&
#118000000
0!
0$
#118500000
1!
1$
#119000000
0!
0$
#119500000
1!
1#
1$
1&
#120000000
0!
0$
#120500000
1!
1$
#121000000
0!
0$
#121500000
1!
0#
1$
0&
#122000000
0!
0$
#122500000
1!
1$
#123000000
0!
0$
#123500000
1!
1#
1$
1&
#124000000
0!
0$
#124500000
1!
1$
#125000000
0!
0$
#125500000
1!
0#
1$
0&
#126000000
0!
0$
#126500000
1!
1$
#127000000
0!
0$
#127500000
1!
1#
1$
1&
#128000000
0!
0$
#128500000
1!
1$
#129000000
0!
0$
#129500000
1!
0#
1$
0&
#130000000
0!
0$
#130500000
1!
1$
#131000000
0!
0$
#131500000
1!
1#
1$
1&
#132000000
0!
0$
#132500000
1!
1$
#133000000
0!
0$
#133500000
1!
0#
1$
0&
#134000000
0!
0$
#134500000
1!
1$
#135000000
0!
0$
#135500000
1!
1#
1$
1&
#136000000
0!
0$
#136500000
1!
1$
#137000000
0!
0$
#137500000
1!
0#
1$
0&
#138000000
0!
0$
#138500000
1!
1$
#139000000
0!
0$
#139500000
1!
1#
1$
1&
#140000000
0!
0$
#140500000
1!
1$
#141000000
0!
0$
#141500000
1!
0#
1$
0&
#142000000
0!
0$
#142500000
1!
1$
#143000000
0!
0$
#143500000
1!
1#
1$
1&
#144000000
0!
b111 "
0$
b111 %
#144500000
1!
1$
#145000000
0!
0$
#145500000
1!
1$
#146000000
0!
0$
#146500000
1!
0#
1$
0&
#147000000
0!
0$
#147500000
1!
1$
#148000000
0!
0$
#148500000
1!
1$
#149000000
0!
0$
#149500000
1!
1#
1$
1&
#150000000
0!
0$
#150500000
1!
1$
#151000000
0!
0$
#151500000
1!
1$
#152000000
0!
0$
#152500000
1!
0#
1$
0&
#153000000
0!
0$
#153500000
1!
1$
#154000000
0!
0$
#154500000
1!
1$
#155000000
0!
0$
#155500000
1!
1#
1$
1&
#156000000
0!
0$
#156500000
1!
1$
#157000000
0!
0$
#157500000
1!
1$
#158000000
0!
0$
#158500000
1!
0#
1$
0&
#159000000
0!
0$
#159500000
1!
1$
#160000000
0!
0$
#160500000
1!
1$
#161000000
0!
0$
#161500000
1!
1#
1$
1&
#162000000
0!
0$
#162500000
1!
1$
#163000000
0!
0$
#163500000
1!
1$
#164000000
0!
0$
#164500000
1!
0#
1$
0&
#165000000
0!
0$
#165500000
1!
1$
#166000000
0!
0$
#166500000
1!
1$
#167000000
0!
0$
#167500000
1!
1#
1$
1&
#168000000
0!
0$
#168500000
1!
1$
#169000000
0!
0$
#169500000
1!
1$
#170000000
0!
0$
#170500000
1!
0#
1$
0&
#171000000
0!
0$
#171500000
1!
1$
#172000000
0!
0$
#172500000
1!
1$
#173000000
0!
0$
#173500000
1!
1#
1$
1&
#174000000
0!
0$
#174500000
1!
1$
#175000000
0!
0$
#175500000
1!
1$
#176000000
0!
0$
#176500000
1!
0#
1$
0&
#177000000
0!
0$
#177500000
1!
1$
#178000000
0!
0$
#178500000
1!
1$
#179000000
0!
0$
#179500000
1!
1#
1$
1&
#180000000
0!
0$
#180500000
1!
1$
#181000000
0!
0$
#181500000
1!
1$
#182000000
0!
0$
#182500000
1!
0#
1$
0&
#183000000
0!
0$
#183500000
1!
1$
#184000000
0!
b0 "
0$
b0 %
